README.md
package_info.json
setup.py
th2_grpc_util/__init__.py
th2_grpc_util/message_comparator_service.py
th2_grpc_util/py.typed
th2_grpc_util/util.proto
th2_grpc_util/util_pb2.py
th2_grpc_util/util_pb2.pyi
th2_grpc_util/util_pb2_grpc.py
th2_grpc_util.egg-info/PKG-INFO
th2_grpc_util.egg-info/SOURCES.txt
th2_grpc_util.egg-info/dependency_links.txt
th2_grpc_util.egg-info/requires.txt
th2_grpc_util.egg-info/top_level.txt